R2Log.py
R2Log-1.0.2.dist-info/LICENSE
R2Log-1.0.2.dist-info/METADATA
R2Log-1.0.2.dist-info/WHEEL
R2Log-1.0.2.dist-info/top_level.txt
R2Log-1.0.2.dist-info/RECORD
