Metadata-Version: 2.1
Name: R2Log
Version: 1.0.2
Summary: Simple python3 custom rich logger ready to go.
Author-email: Dramelac <dramelac@pm.me>
License: GNU GENERAL PUBLIC LICENSE
Project-URL: Repository, https://github.com/Dramelac/R2Log
Project-URL: Issues, https://github.com/Dramelac/R2Log/issues
Keywords: logger,dev
Classifier: Development Status :: 5 - Production/Stable
Classifier: Programming Language :: Python :: 3.6
Classifier: Programming Language :: Python :: 3.7
Classifier: Programming Language :: Python :: 3.8
Classifier: Programming Language :: Python :: 3.9
Classifier: Programming Language :: Python :: 3.10
Classifier: Programming Language :: Python :: 3.11
Classifier: Programming Language :: Python :: 3.12
Classifier: License :: OSI Approved :: GNU General Public License v3 (GPLv3)
Classifier: Operating System :: OS Independent
Requires-Python: >=3.6
License-File: LICENSE
Requires-Dist: rich >=11.2.0
